archmd/__init__.py
archmd-0.3.0.dist-info/METADATA
archmd-0.3.0.dist-info/WHEEL
archmd-0.3.0.dist-info/LICENSE
archmd-0.3.0.dist-info/entry_points.txt
archmd-0.3.0.dist-info/RECORD
