Metadata-Version: 2.1
Name: archmd
Version: 0.3.0
Summary: A simple command line utility to build an architecture.md file
Author: Joel Collins
Author-email: pypi@jtcollins.net
Requires-Python: >=3.8,<4.0
Classifier: Programming Language :: Python :: 3
Classifier: Programming Language :: Python :: 3.8
Classifier: Programming Language :: Python :: 3.9
Classifier: Programming Language :: Python :: 3.10
Classifier: Programming Language :: Python :: 3.11
Requires-Dist: typer (>=0.9.0,<0.10.0)
